agilent_format/__init__.py
agilent_format/agilent.py
agilent_format/datasets/4_noimage_agg256.bsp
agilent_format/datasets/4_noimage_agg256.dat
agilent_format/datasets/4_noimage_agg256.hdr
agilent_format/datasets/4_noimage_agg256.seq
agilent_format/datasets/5_Mosaic_agg1024.dat
agilent_format/datasets/5_Mosaic_agg1024.dms
agilent_format/datasets/5_Mosaic_agg1024_0000_0000.dmd
agilent_format/datasets/5_Mosaic_agg1024_0000_0000.drd
agilent_format/datasets/5_Mosaic_agg1024_0000_0001.dmd
agilent_format/datasets/5_Mosaic_agg1024_0000_0001.drd
agilent_format/datasets/5_mosaic_agg1024.dmt
agilent_format/datasets/5_mosaic_agg1024.hdr
agilent_format/datasets/IrCutout.bmp
agilent_format/datasets/IrMosaicInfo.cfg
agilent_format/datasets/VisMosaicCollectImages_Thumbnail.bmp
agilent_format/datasets/VisMosaicInfo.cfg
agilent_format/datasets/background_agg1024.bsp
agilent_format/datasets/background_agg1024.dat
agilent_format/datasets/background_agg1024.seq
agilent_format/datasets/background_agg256.bsp
agilent_format/datasets/background_agg256.dat
agilent_format/datasets/background_agg256.seq
agilent_format/tests/__init__.py
agilent_format/tests/test_filenames.py
agilent_format/tests/test_image.py
agilent_format/tests/test_image_ifg.py
agilent_format/tests/test_mosaic.py
agilent_format/tests/test_mosiac_ifg.py
agilent_format/tests/test_utils.py
agilent_format-0.4.7.dist-info/licenses/LICENSE
agilent_format-0.4.7.dist-info/METADATA
agilent_format-0.4.7.dist-info/WHEEL
agilent_format-0.4.7.dist-info/top_level.txt
agilent_format-0.4.7.dist-info/RECORD
