Metadata-Version: 2.4
Name: agilent-format
Version: 0.4.7
Summary: File reader for Agilent Resolutions Pro FT-IR images
Author-email: Stuart Read <stuart.read@lightsource.ca>
Project-URL: Homepage, https://github.com/stuart-cls/python-agilent-file-formats
Project-URL: Issues, https://github.com/stuart-cls/python-agilent-file-formats/issues
Classifier: Programming Language :: Python :: 3
Classifier: License :: OSI Approved :: MIT License
Classifier: Operating System :: OS Independent
Requires-Python: >=3.10
License-File: LICENSE
Requires-Dist: numpy
Dynamic: license-file
